flachtex/__init__.py
flachtex/__main__.py
flachtex/command_finder.py
flachtex/command_substitution.py
flachtex/comments.py
flachtex/cycle_prevention.py
flachtex/filefinder.py
flachtex/main.py
flachtex/preprocessor.py
flachtex/py.typed
flachtex/traceable_string.py
flachtex/utils.py
flachtex/rules/__init__.py
flachtex/rules/import_rules.py
flachtex/rules/skip_rules.py
flachtex/rules/subimport_substiution_rules.py
flachtex/rules/substitution_rules.py
flachtex-0.6.0.dist-info/licenses/LICENSE
flachtex-0.6.0.dist-info/METADATA
flachtex-0.6.0.dist-info/WHEEL
flachtex-0.6.0.dist-info/entry_points.txt
flachtex-0.6.0.dist-info/top_level.txt
flachtex-0.6.0.dist-info/RECORD
