Metadata-Version: 2.4
Name: flachtex
Version: 0.6.0
Summary: A traceable LaTeX flattener
Author-email: Dominik Krupke <krupke@ibr.cs.tu-bs.de>
License: MIT
Project-URL: Homepage, https://github.com/d-krupke/flachtex
Project-URL: Repository, https://github.com/d-krupke/flachtex
Project-URL: Issues, https://github.com/d-krupke/flachtex/issues
Keywords: LaTeX,flatten,preprocessing
Classifier: Development Status :: 4 - Beta
Classifier: License :: OSI Approved :: MIT License
Classifier: Programming Language :: Python :: 3
Classifier: Programming Language :: Python :: 3.10
Classifier: Programming Language :: Python :: 3.11
Classifier: Programming Language :: Python :: 3.12
Classifier: Intended Audience :: Science/Research
Classifier: Topic :: Text Processing :: Markup :: LaTeX
Classifier: Typing :: Typed
Requires-Python: >=3.10
License-File: LICENSE
Dynamic: license-file
